{
    "run": {
        "configuration": {
            "agent": {
                "plan": "off",
                "trial": "off",
                "action": "direct",
                "observe": "off",
                "reflect": "off",
                "memory_type": "simple"
            },
            "perception": "all",
            "position": "relative",
            "temperature": 0.0,
            "name": "baseline-naive",
            "seed": 12345
        },
        "model_team": {
            "name": "Llama3-Groq-8B-Q8-Toolcalling",
            "imaginator": "None",
            "realisator": "Llama3-Groq-8B-Q8-Toolcalling"
        },
        "level": {
            "name": "carrot-hard-detailed",
            "difficulty": "hard",
            "accuracy": "detailed",
            "optimal_steps": 1
        },
        "reruns": 5,
        "optimal_steps_multiplier": 3.0
    },
    "hostname": "c3poxxx",
    "success_rate": 1.0,
    "toolcall_count": 36,
    "actions_external": 36,
    "actions_internal": 0,
    "softerror_count": 26,
    "harderror_count": 20,
    "step_count": 2,
    "time_s": 37.77317214012146,
    "img_time_s": 0,
    "real_time_s": 37.766650915145874,
    "plan_time_s": 1.6689300537109375e-06,
    "observe_time_s": 1.9073486328125e-06,
    "trial_time_s": 9.5367431640625e-07,
    "action_time_s": 37.77028751373291,
    "reflect_time_s": 0.00010156631469726562
}