{
    "run": {
        "configuration": {
            "agent": {
                "plan": "off",
                "trial": "off",
                "action": "imaginator",
                "observe": "off",
                "reflect": "off",
                "memory_type": "simple"
            },
            "perception": "all",
            "position": "relative",
            "temperature": 0.0,
            "name": "baseline-img",
            "seed": 12345
        },
        "model_team": {
            "name": "Llama3.1-nemotron-8B",
            "imaginator": "None",
            "realisator": "Llama3.1-nemotron-8B"
        },
        "level": {
            "name": "carrot-hard-vague",
            "difficulty": "hard",
            "accuracy": "vague",
            "optimal_steps": 1
        },
        "reruns": 1,
        "optimal_steps_multiplier": 3.0
    },
    "hostname": "c3poxxx",
    "success_rate": 0.0,
    "toolcall_count": 10,
    "actions_external": 10,
    "actions_internal": 0,
    "softerror_count": 12,
    "harderror_count": 7,
    "step_count": 4,
    "time_s": 9.766931295394897,
    "img_time_s": 1.8728234767913818,
    "real_time_s": 7.88653826713562,
    "plan_time_s": 7.152557373046875e-06,
    "observe_time_s": 9.5367431640625e-06,
    "trial_time_s": 4.0531158447265625e-06,
    "action_time_s": 9.760111093521118,
    "reflect_time_s": 6.937980651855469e-05
}