{
    "run": {
        "configuration": {
            "agent": {
                "plan": "off",
                "trial": "off",
                "action": "direct",
                "observe": "off",
                "reflect": "off",
                "memory_type": "simple"
            },
            "perception": "all",
            "position": "relative",
            "temperature": 0.0,
            "name": "baseline-naive",
            "seed": 12345
        },
        "model_team": {
            "name": "Llama3.1-nemotron-8B",
            "imaginator": "None",
            "realisator": "Llama3.1-nemotron-8B"
        },
        "level": {
            "name": "cucumber-hard-detailed",
            "difficulty": "hard",
            "accuracy": "detailed",
            "optimal_steps": 3
        },
        "reruns": 2,
        "optimal_steps_multiplier": 3.0
    },
    "hostname": "c3poxxx",
    "success_rate": 0.0,
    "toolcall_count": 10,
    "actions_external": 10,
    "actions_internal": 0,
    "softerror_count": 6,
    "harderror_count": 4,
    "step_count": 10,
    "time_s": 10.18015742301941,
    "img_time_s": 0,
    "real_time_s": 10.158531188964844,
    "plan_time_s": 2.2172927856445312e-05,
    "observe_time_s": 1.4066696166992188e-05,
    "trial_time_s": 8.106231689453125e-06,
    "action_time_s": 10.159442901611328,
    "reflect_time_s": 0.0001614093780517578
}