{
    "run": {
        "configuration": {
            "agent": {
                "plan": "off",
                "trial": "off",
                "action": "img_retry",
                "observe": "off",
                "reflect": "off",
                "memory_type": "simple"
            },
            "perception": "all",
            "position": "relative",
            "temperature": 0.0,
            "name": "imginator-retry",
            "seed": 12345
        },
        "model_team": {
            "name": "Magistral-Small-24B",
            "imaginator": "None",
            "realisator": "Magistral-Small-24B"
        },
        "level": {
            "name": "pepper-easy-detailed",
            "difficulty": "easy",
            "accuracy": "detailed",
            "optimal_steps": 12
        },
        "reruns": 4,
        "optimal_steps_multiplier": 3.0
    },
    "hostname": "bb8xxx",
    "success_rate": 0.0,
    "toolcall_count": 2,
    "actions_external": 2,
    "actions_internal": 0,
    "softerror_count": 2,
    "harderror_count": 49,
    "step_count": 37,
    "time_s": 3436.7645847797394,
    "img_time_s": 1654.4423186779022,
    "real_time_s": 1781.3336894512177,
    "plan_time_s": 4.57763671875e-05,
    "observe_time_s": 7.43865966796875e-05,
    "trial_time_s": 2.6941299438476562e-05,
    "action_time_s": 3436.0565094947815,
    "reflect_time_s": 9.131431579589844e-05
}