{
    "run": {
        "configuration": {
            "agent": {
                "plan": "off",
                "trial": "off",
                "action": "img_retry",
                "observe": "off",
                "reflect": "off",
                "memory_type": "simple"
            },
            "perception": "all",
            "position": "relative",
            "temperature": 0.0,
            "name": "imginator-retry",
            "seed": 12345
        },
        "model_team": {
            "name": "Llama3.1-nemotron-8B",
            "imaginator": "None",
            "realisator": "Llama3.1-nemotron-8B"
        },
        "level": {
            "name": "pepper-hard-vague",
            "difficulty": "hard",
            "accuracy": "vague",
            "optimal_steps": 12
        },
        "reruns": 2,
        "optimal_steps_multiplier": 3.0
    },
    "hostname": "gonkxxx",
    "success_rate": 0.0,
    "toolcall_count": 50,
    "actions_external": 50,
    "actions_internal": 0,
    "softerror_count": 38,
    "harderror_count": 16,
    "step_count": 37,
    "time_s": 145.43142533302307,
    "img_time_s": 70.15692377090454,
    "real_time_s": 75.19045495986938,
    "plan_time_s": 6.4849853515625e-05,
    "observe_time_s": 5.173683166503906e-05,
    "trial_time_s": 2.86102294921875e-05,
    "action_time_s": 145.35071229934692,
    "reflect_time_s": 0.0005340576171875
}