{
    "run": {
        "configuration": {
            "agent": {
                "plan": "off",
                "trial": "off",
                "action": "img_retry",
                "observe": "off",
                "reflect": "off",
                "memory_type": "simple"
            },
            "perception": "all",
            "position": "relative",
            "temperature": 0.0,
            "name": "imginator-retry",
            "seed": 12345
        },
        "model_team": {
            "name": "Llama3.1-nemotron-8B",
            "imaginator": "None",
            "realisator": "Llama3.1-nemotron-8B"
        },
        "level": {
            "name": "pepper-easy-vague",
            "difficulty": "easy",
            "accuracy": "vague",
            "optimal_steps": 12
        },
        "reruns": 5,
        "optimal_steps_multiplier": 3.0
    },
    "hostname": "gonkxxx",
    "success_rate": 0.0,
    "toolcall_count": 45,
    "actions_external": 45,
    "actions_internal": 0,
    "softerror_count": 74,
    "harderror_count": 11,
    "step_count": 37,
    "time_s": 127.6758770942688,
    "img_time_s": 71.55503821372986,
    "real_time_s": 56.036566495895386,
    "plan_time_s": 5.626678466796875e-05,
    "observe_time_s": 5.340576171875e-05,
    "trial_time_s": 2.5987625122070312e-05,
    "action_time_s": 127.59477615356445,
    "reflect_time_s": 0.0005626678466796875
}